{
  "id": "index",
  "title": "TALA Documentation",
  "description": "TALA — Multi-tenant accounting system with BIR compliance, cryptographic audit trails, and role-based access control.",
  "source": "@site/docs/index.md",
  "sourceDirName": ".",
  "slug": "/",
  "permalink": "/",
  "draft": false,
  "unlisted": false,
  "tags": [],
  "version": "current",
  "frontMatter": {},
  "sidebar": "docs",
  "next": {
    "title": "Annex C-1 — System Process Flow",
    "permalink": "/compliance/annex-c1-process-flow"
  }
}